oschmod/__init__.py
oschmod/cli.py
oschmod-0.3.12.dist-info/LICENSE
oschmod-0.3.12.dist-info/METADATA
oschmod-0.3.12.dist-info/WHEEL
oschmod-0.3.12.dist-info/entry_points.txt
oschmod-0.3.12.dist-info/top_level.txt
oschmod-0.3.12.dist-info/RECORD
